torchpf/__init__.py
torchpf/__main__.py
torchpf/compute_flops.py
torchpf/compute_madd.py
torchpf/compute_memory.py
torchpf/model_hook.py
torchpf/reporter.py
torchpf/stat_tree.py
torchpf/statistics.py
torchpf-0.1.0.dist-info/LICENSE
torchpf-0.1.0.dist-info/METADATA
torchpf-0.1.0.dist-info/WHEEL
torchpf-0.1.0.dist-info/top_level.txt
torchpf-0.1.0.dist-info/RECORD
